sosaa_gui/__init__.py
sosaa_gui/__main__.py
sosaa_gui/config.py
sosaa_gui/qt.py
sosaa_gui/resources.py
sosaa_gui/style.py
sosaa_gui/version.py
sosaa_gui/conf/minimal.init
sosaa_gui/gui/__init__.py
sosaa_gui/gui/browse.py
sosaa_gui/gui/compile.py
sosaa_gui/gui/dirs.py
sosaa_gui/gui/help.py
sosaa_gui/gui/loadsave.py
sosaa_gui/gui/modules.py
sosaa_gui/gui/output.py
sosaa_gui/gui/run.py
sosaa_gui/gui/scenario.py
sosaa_gui/gui/style.py
sosaa_gui/gui/syntax.py
sosaa_gui/gui/terminal.py
sosaa_gui/gui/rsm/__init__.py
sosaa_gui/gui/rsm/build.py
sosaa_gui/gui/rsm/predict.py
sosaa_gui/gui/rsm/progress.py
sosaa_gui/gui/rsm/worker.py
sosaa_gui/gui/rsm/plot/__init__.py
sosaa_gui/gui/rsm/plot/ccn.py
sosaa_gui/gui/rsm/plot/diff.py
sosaa_gui/icons/load.svg
sosaa_gui/icons/recompile.svg
sosaa_gui/icons/save-as.svg
sosaa_gui/icons/save-defaults.svg
sosaa_gui/icons/save-inactive.svg
sosaa_gui/icons/save.svg
sosaa_gui/icons/sosaa-icon.svg
sosaa_gui/icons/sosaa-splash-dark.svg
sosaa_gui/icons/sosaa-splash-light.svg
sosaa_gui/layouts/about.py
sosaa_gui/layouts/gui.py
sosaa_gui/settings/__init__.py
sosaa_gui/settings/from_file.py
sosaa_gui/settings/from_gui.py
sosaa_gui/sosaa_rsm/__init__.py
sosaa_gui/sosaa_rsm/dataset/__init__.py
sosaa_gui/sosaa_rsm/dataset/clump.py
sosaa_gui/sosaa_rsm/dataset/expand.py
sosaa_gui/sosaa_rsm/dataset/netcdf.py
sosaa_gui/sosaa_rsm/dataset/paths.py
sosaa_gui/sosaa_rsm/dataset/utils.py
sosaa_gui/sosaa_rsm/dataset/features/__init__.py
sosaa_gui/sosaa_rsm/dataset/features/extract/__init__.py
sosaa_gui/sosaa_rsm/dataset/features/extract/aerosol.py
sosaa_gui/sosaa_rsm/dataset/features/extract/anthropogenic.py
sosaa_gui/sosaa_rsm/dataset/features/extract/biogenic.py
sosaa_gui/sosaa_rsm/dataset/features/extract/meteorology.py
sosaa_gui/sosaa_rsm/dataset/labels/__init__.py
sosaa_gui/sosaa_rsm/dataset/labels/ccn.py
sosaa_gui/sosaa_rsm/dataset/labels/time.py
sosaa_gui/sosaa_rsm/icarus/__init__.py
sosaa_gui/sosaa_rsm/icarus/analyse.py
sosaa_gui-0.1.0.dist-info/LICENSE
sosaa_gui-0.1.0.dist-info/LICENSE-GPL
sosaa_gui-0.1.0.dist-info/METADATA
sosaa_gui-0.1.0.dist-info/WHEEL
sosaa_gui-0.1.0.dist-info/entry_points.txt
sosaa_gui-0.1.0.dist-info/top_level.txt
sosaa_gui-0.1.0.dist-info/RECORD
