Metadata-Version: 2.1
Name: sosaa-gui
Version: 0.1.0
Summary: Graphical User Interface for Configuring, Running, and Approximating the SOSAA Model
Author-email: Juniper Tyree <juniper.tyree@helsinki.fi>, Petri Clusius <petri.clusius@helsinki.fi>, Multi-Scale Modelling group <sosaa@helsinki.fi>
Maintainer-email: Multi-Scale Modelling group <sosaa@helsinki.fi>
License: GNU GENERAL PUBLIC LICENSE
Requires-Python: >=3.7
License-File: LICENSE
License-File: LICENSE-GPL
Requires-Dist: darkdetect (>=0.7.1)
Requires-Dist: f90nml (>=1.4.3)
Requires-Dist: PyQt5 (>=5.15.7)
Provides-Extra: dev
Requires-Dist: black ; extra == 'dev'
Requires-Dist: build ; extra == 'dev'
Requires-Dist: bumpver ; extra == 'dev'
Requires-Dist: pyproject-flake8 ; extra == 'dev'
Requires-Dist: isort ; extra == 'dev'
Requires-Dist: twine ; extra == 'dev'
Provides-Extra: icarus
Requires-Dist: matplotlib (>=3.5.2) ; extra == 'icarus'
Requires-Dist: joblib (>=1.2.0) ; extra == 'icarus'
Requires-Dist: netcdf4 (>=1.5.4) ; extra == 'icarus'
Requires-Dist: numpy (>=1.23.4) ; extra == 'icarus'
Requires-Dist: pandas (>=1.4.4) ; extra == 'icarus'
Requires-Dist: scipy (>=1.9.3) ; extra == 'icarus'
Requires-Dist: scikit-learn (>=1.1.2) ; extra == 'icarus'
